circular_clustering/__init__.py
circular_clustering/circular_interval.py
circular_clustering/circular_k_means_weighted.py
circular_clustering/circular_x_means_quantiles.py
circular_clustering/cylindrical_hdr.py
circular_clustering/cylindrical_hdr_x_means.py
circular_clustering/cylindrical_hdrpp_merge.py
circular_clustering/cylindrical_k_means.py
circular_clustering/kmeans_1d.py
circular_clustering/optimal_circular_kmeans.py
circular_clustering-0.0.12.dist-info/licenses/LICENSE
circular_clustering-0.0.12.dist-info/METADATA
circular_clustering-0.0.12.dist-info/WHEEL
circular_clustering-0.0.12.dist-info/top_level.txt
circular_clustering-0.0.12.dist-info/RECORD
