Metadata-Version: 2.4
Name: circular_clustering
Version: 0.0.12
Summary: Adaptation of X means algorithm for circular and cylindrical data
Author: Hugo J. Bello
Author-email: hjbello.wk@protonmail.com
License: MIT
Requires-Python: >=3.7
License-File: LICENSE
Requires-Dist: numpy
Requires-Dist: scipy
Requires-Dist: matplotlib
Dynamic: license-file
